Metadata-Version: 1.1
Name: licenseit
Version: 0.1.1
Summary: CLI for generationg a license files.
Home-page: https://github.com/monzita/licenseit
Author: Monika Ilieva
Author-email: hidden@hidden.com
License: MIT
Keywords: cli license generator
Platform: UNKNOWN
Classifier: Development Status :: 3 - Alpha
Classifier: Environment :: Console
Classifier: Intended Audience :: Developers
Classifier: License :: OSI Approved :: MIT License
Classifier: Programming Language :: Python :: 3.5
Classifier: Programming Language :: Python :: 3.6
Classifier: Programming Language :: Python :: 3.7
Classifier: Programming Language :: Python :: 3.8
Classifier: Programming Language :: Python :: 3 :: Only
Classifier: Topic :: Utilities
